dataannotation/__init__.py
dataannotation/module1.py
dataannotation/module2.py
dataannotation-1.0.0.dist-info/LICENSE
dataannotation-1.0.0.dist-info/METADATA
dataannotation-1.0.0.dist-info/WHEEL
dataannotation-1.0.0.dist-info/top_level.txt
dataannotation-1.0.0.dist-info/RECORD
