Metadata-Version: 2.1
Name: dataannotation
Version: 1.0.0
Summary: This is just a test package
Home-page: https://github.com/waqasmansoor/dataannotation
Author: Waqas
Author-email: waqasmansoor47@yahoo.com
Classifier: Programming Language :: Python :: 3
Classifier: License :: OSI Approved :: MIT License
Classifier: Operating System :: OS Independent
Requires-Python: >=3.6
License-File: LICENSE
